chat/__init__.py
chat/admin.py
chat/apps.py
chat/consumers.py
chat/models.py
chat/routing.py
chat/tests.py
chat/urls.py
chat/views.py
chat/migrations/__init__.py
ingredients/__init__.py
ingredients/admin.py
ingredients/apps.py
ingredients/models.py
ingredients/schema.py
ingredients/tests.py
ingredients/views.py
ingredients/migrations/0001_initial.py
ingredients/migrations/__init__.py
mainapp/__init__.py
mainapp/asgi.py
mainapp/consumers.py
mainapp/routing.py
mainapp/schema.py
mainapp/settings.py
mainapp/signals.py
mainapp/subscription.py
mainapp/urls.py
mainapp/views.py
mainapp/wsgi.py
mtgapi/__init__.py
mtgapi/main.py
mtproxy/__init__.py
mtproxy/admin.py
mtproxy/apps.py
mtproxy/models.py
mtproxy/schema.py
mtproxy/signals.py
mtproxy/tests.py
mtproxy/urls.py
mtproxy/views.py
mtproxy/management/__init__.py
mtproxy/management/commands/__init__.py
mtproxy/management/commands/msg_comsumer.py
mtproxy/management/commands/msg_productor.py
mtproxy/management/commands/onion_gen.py
mtproxy/management/commands/onion_up.py
mtproxy/migrations/0001_initial.py
mtproxy/migrations/0002_auto_20220118_1312.py
mtproxy/migrations/0003_auto_20220119_1842.py
mtproxy/migrations/0004_alter_sshhost_port.py
mtproxy/migrations/0005_auto_20220119_1850.py
mtproxy/migrations/0006_alter_portforward_lhost.py
mtproxy/migrations/0007_portforward_enabled.py
mtproxy/migrations/0008_alter_portforward_proto.py
mtproxy/migrations/0009_auto_20220119_1905.py
mtproxy/migrations/0010_auto_20220121_1233.py
mtproxy/migrations/0011_auto_20220121_1240.py
mtproxy/migrations/0012_bot_onion_onionbot.py
mtproxy/migrations/0013_bot_owner.py
mtproxy/migrations/0014_auto_20220122_0343.py
mtproxy/migrations/0015_auto_20220122_0346.py
mtproxy/migrations/0016_auto_20220122_0358.py
mtproxy/migrations/0017_script.py
mtproxy/migrations/0018_script_markdown_content.py
mtproxy/migrations/0019_auto_20220122_0508.py
mtproxy/migrations/0020_botlog.py
mtproxy/migrations/0021_botlog_bot.py
mtgapi-0.0.2.dist-info/METADATA
mtgapi-0.0.2.dist-info/WHEEL
mtgapi-0.0.2.dist-info/entry_points.txt
mtgapi-0.0.2.dist-info/top_level.txt
mtgapi-0.0.2.dist-info/RECORD
