Metadata-Version: 2.1
Name: mtgapi
Version: 0.0.2
Summary: This is the SDK for example.
Home-page: http://example.com
Author: example
Author-email: author@example.com
License: UNKNOWN
Platform: UNKNOWN
Classifier: License :: OSI Approved :: MIT License
Classifier: Intended Audience :: Developers
Classifier: Operating System :: OS Independent
Classifier: Programming Language :: Python
Classifier: Programming Language :: Python :: 2
Classifier: Programming Language :: Python :: 2.6
Classifier: Programming Language :: Python :: 2.7
Classifier: Programming Language :: Python :: 3
Classifier: Programming Language :: Python :: 3.3
Classifier: Programming Language :: Python :: 3.4
Classifier: Programming Language :: Python :: 3.5
Requires-Dist: requests (!=2.9.0)
Requires-Dist: lxml (>=4.2.3)
Requires-Dist: monotonic (>=1.5)
Requires-Dist: django (==3.2.11)
Requires-Dist: graphene-django
